rfic/__init__.py
valuation/__init__.py
venv/bin/rst2html.py
venv/bin/rst2html4.py
venv/bin/rst2html5.py
venv/bin/rst2latex.py
venv/bin/rst2man.py
venv/bin/rst2odt.py
venv/bin/rst2odt_prepstyles.py
venv/bin/rst2pseudoxml.py
venv/bin/rst2s5.py
venv/bin/rst2xetex.py
venv/bin/rst2xml.py
venv/bin/rstpep2html.py
RFIC-0.0.93.dist-info/METADATA
RFIC-0.0.93.dist-info/WHEEL
RFIC-0.0.93.dist-info/top_level.txt
RFIC-0.0.93.dist-info/RECORD
