Metadata-Version: 2.1
Name: RFIC
Version: 0.0.93
Summary: Reed College Finance and Investment Club (RFIC)
Home-page: UNKNOWN
Author: Blaise Albis-Burdige
Author-email: albisbub@reed.edu
License: UNKNOWN
Platform: UNKNOWN
Classifier: Programming Language :: Python :: 3
Classifier: License :: OSI Approved :: MIT License
Classifier: Operating System :: OS Independent
Requires-Python: >=3.6
